lattica_common/__init__.py
lattica_common/app_api.py
lattica_common/definitions.py
lattica_common/http_settings.py
lattica_common/version_utils.py
lattica_common/dev_utils/dev_mod_utils.py
lattica_common-0.7.0.dist-info/METADATA
lattica_common-0.7.0.dist-info/WHEEL
lattica_common-0.7.0.dist-info/top_level.txt
lattica_common-0.7.0.dist-info/RECORD
