Metadata-Version: 2.4
Name: lattica-common
Version: 0.7.0
Summary: Common functions for Lattica clients
Author-email: "LatticaAI Inc." <hello@lattica.ai>
Project-URL: Homepage, https://lattica.ai
Requires-Python: >=3.11
Requires-Dist: requests>=2.31.0
